<?xml version="1.0" encoding="UTF-8" ?>
<!DOCTYPE mapper PUBLIC "-//mybatis.org//DTD Mapper 3.0//EN" 
	"http://mybatis.org/dtd/mybatis-3-mapper.dtd">

<mapper namespace="com.ssafy.happyhouse.model.mapper.HouseDealMapper">

	<select id="searchAll" resultType="HouseDealDto">
		select *
		from housedeal
		limit 0, 100
	</select>
	
	<select id="search" parameterType="String" resultType="HouseDealDto">
		select *
		from housedeal
		where no = #{no}
	</select>
	
	<select id="searchApt" parameterType="String" resultType="HouseDealDto">
		select *
		from housedeal
		where aptname like CONCAT('%', #{aptname}, '%')
	</select>
	
	<select id="searchDong" parameterType="String" resultType="HouseDealDto">
		select *
		from housedeal
		where dong like #{dong}
	</select>
	
	<select id="searchType" parameterType="String" resultType="HouseDealDto">
		select *
		from housedeal
		where type = #{type}
	</select>
	
	<select id="searchSido" resultType="SidoGugunCodeDto">
		select sido_code as sidoCode, sido_name as sidoName
		from sidocode
	</select>
	
	<select id="searchGugun" resultType="SidoGugunCodeDto">
 		select gugun_code as gugunCode, gugun_name as gugunName from guguncode
	</select>
	
	<select id="searchDongName" resultType="DongCodeDto">
 		select dongcode, dong from dongcode
	</select>
	
	<select id="searchDetail" parameterType="String" resultType="HouseDealDto">
		select *
		from housedeal
		where no like #{no}
	</select>

</mapper>